{
  "clat-post-february-2026-part-2-merge-organized-compressed-0294740414a38.pdf": {
    "pages": 100,
    "estimated_questions": 36,
    "estimated_passages": 0,
    "topics_found": [],
    "sample_lines": [
      "--- Page 1 ---",
      "--- Page 2 ---",
      "support@toprankers.com",
      "6363 28 6363",
      "www.toprankers.com"
    ]
  },
  "the-clat-post-april-2026-part-2-compressed-02966ae74af78.pdf": {
    "pages": 98,
    "estimated_questions": 36,
    "estimated_passages": 0,
    "topics_found": [],
    "sample_lines": [
      "--- Page 1 ---",
      "\u001b\u001a\u0019\u0018\u0017\u0016\u001a\u0015\u001e\u0014\u001c\u0013",
      "covering news from 16th To 30th  April",
      "--- Page 2 ---",
      "support@toprankers.com"
    ]
  },
  "the-clat-post-february-2026-edition-reupload-0294295044a61.pdf": {
    "pages": 252,
    "estimated_questions": 116,
    "estimated_passages": 0,
    "topics_found": [
      "International Affairs"
    ],
    "sample_lines": [
      "--- Page 1 ---",
      "Current Affairs",
      "from 1st January to 31st January, 2026",
      "JANUARY 2026",
      "CA from 1st January to 31st January, 2026"
    ]
  },
  "the-clat-post-february-2026-part-a--0293f7d79e3f4.pdf": {
    "pages": 77,
    "estimated_questions": 43,
    "estimated_passages": 0,
    "topics_found": [],
    "sample_lines": [
      "--- Page 1 ---",
      "--- Page 2 ---",
      "THE NEW \u201c+\u201d IN CLAT POST",
      "To make your preparation lighter and more focused, we\u2019re introducing a new 15-day magazine format",
      "with priority-based topics."
    ]
  },
  "the-clat-post-june-2026-part-a--0297eb6c533fa.pdf": {
    "pages": 109,
    "estimated_questions": 30,
    "estimated_passages": 0,
    "topics_found": [],
    "sample_lines": [
      "--- Page 1 ---",
      "--- Page 2 ---",
      "support@toprankers.com",
      "6363 28 6363",
      "www.toprankers.com"
    ]
  },
  "the-clat-post-june-part-02-compressed-029877d01dc82.pdf": {
    "pages": 99,
    "estimated_questions": 191,
    "estimated_passages": 0,
    "topics_found": [],
    "sample_lines": [
      "--- Page 1 ---",
      "--- Page 2 ---",
      "support@toprankers.com",
      "6363 28 6363",
      "www.toprankers.com"
    ]
  },
  "the-clat-post-march-2026-part-2-029568dae17f5.pdf": {
    "pages": 126,
    "estimated_questions": 32,
    "estimated_passages": 0,
    "topics_found": [],
    "sample_lines": [
      "--- Page 1 ---",
      "--- Page 2 ---",
      "support@toprankers.com",
      "6363 28 6363",
      "www.toprankers.com"
    ]
  },
  "the-clat-post-march-part-1-0294f59cf598c.pdf": {
    "pages": 93,
    "estimated_questions": 35,
    "estimated_passages": 0,
    "topics_found": [],
    "sample_lines": [
      "--- Page 1 ---",
      "--- Page 2 ---",
      "support@toprankers.com",
      "6363 28 6363",
      "www.toprankers.com"
    ]
  },
  "the-clat-post-may-2026-part-01-0296ed59bf171.pdf": {
    "pages": 105,
    "estimated_questions": 41,
    "estimated_passages": 0,
    "topics_found": [],
    "sample_lines": [
      "--- Page 1 ---",
      "--- Page 2 ---",
      "support@toprankers.com",
      "6363 28 6363",
      "www.toprankers.com"
    ]
  },
  "the-clat-post-may-2026-part-2-02975766423be.pdf": {
    "pages": 100,
    "estimated_questions": 46,
    "estimated_passages": 0,
    "topics_found": [],
    "sample_lines": [
      "--- Page 1 ---",
      "--- Page 2 ---",
      "support@toprankers.com",
      "6363 28 6363",
      "www.toprankers.com"
    ]
  }
}